baseballforecaster.py
baseballforecaster-0.0.7.dist-info/License.txt
baseballforecaster-0.0.7.dist-info/METADATA
baseballforecaster-0.0.7.dist-info/WHEEL
baseballforecaster-0.0.7.dist-info/top_level.txt
baseballforecaster-0.0.7.dist-info/RECORD
