Metadata-Version: 2.1
Name: baseballforecaster
Version: 0.0.7
Summary: A monte-carlo forecaster and drafter for baseball performance
Home-page: https://github.com/baileymorton989/baseballforecaster
Author: Bailey Morton
Author-email: baileymorton989@gmail.com
License: MIT License
Platform: UNKNOWN
Classifier: Programming Language :: Python :: 3
Classifier: Programming Language :: Python :: 3.6
Classifier: Programming Language :: Python :: 3.7
Classifier: Programming Language :: Python :: 3.8
Classifier: Programming Language :: Python :: 3.9
Classifier: License :: OSI Approved :: MIT License
Classifier: Operating System :: OS Independent
Requires-Dist: pybaseball (>=2.1.1)
Requires-Dist: pandas (>=1.1.4)
Requires-Dist: numpy (>=1.18.1)
Requires-Dist: scikit-learn (>=0.23.1)
Requires-Dist: tqdm (>=4.47.0)
Provides-Extra: dev
Requires-Dist: pytest (>3.7) ; extra == 'dev'
